{
  "schema_version": "v4.1",
  "created_at": "2026-03-31T15:28:59.298974+00:00",
  "record_id": "a59b0421e443ae91",
  "circuit_id": "40d41b46f16e7a42",
  "noise_source": {
    "json_file": "ibm_marrakesh_representative_1_2025-05-06T00_00_00_00_00.json",
    "query_datetime": "2025-05-06T00:00:00+00:00",
    "backend_name": "ibm_marrakesh",
    "fake_backend": "fake_marrakesh",
    "noise_summary": {
      "T1_mean": 215.481747115048,
      "T2_mean": 135.62021222633922,
      "prob_meas0_prep1_mean": 0.029972956730769232,
      "prob_meas1_prep0_mean": 0.023274739583333332,
      "sx_gate_error_mean": 0.0071339761111955564,
      "twoq_gate_error_mean": 0.01309083658108124
    }
  },
  "transpile": {
    "optimization_level": 1,
    "seed_transpiler": 1234
  },
  "fidelity_definition": "hellinger_fidelity_(sum_sqrt(pq))^2_vs_statevector_ideal",
  "real_fidelity_curve": {
    "shots_sequence": [
      50,
      62,
      78,
      98,
      122,
      153,
      191
    ],
    "sample_reps": 30,
    "summary": {
      "50": {
        "mean": 0.2043311124229728,
        "std": 0.07724010137351292,
        "p05": 0.08587321729311306,
        "p50": 0.20049276910128477,
        "p95": 0.33198026383490786
      },
      "62": {
        "mean": 0.2357784949631723,
        "std": 0.05423621847912541,
        "p05": 0.1593824042475207,
        "p50": 0.2307143569418234,
        "p95": 0.31521064948278615
      },
      "78": {
        "mean": 0.22593685859728208,
        "std": 0.04276931455690985,
        "p05": 0.15401560308941117,
        "p50": 0.2269728574142371,
        "p95": 0.29736203566062597
      },
      "98": {
        "mean": 0.24200397060207582,
        "std": 0.03790385749053502,
        "p05": 0.1864306093275071,
        "p50": 0.2387830743426893,
        "p95": 0.2952270598615155
      },
      "122": {
        "mean": 0.2548490142163893,
        "std": 0.049371935977136835,
        "p05": 0.19436195711608945,
        "p50": 0.24920030859904738,
        "p95": 0.33865220784930367
      },
      "153": {
        "mean": 0.25084775514691954,
        "std": 0.041186111867394196,
        "p05": 0.18906345146046916,
        "p50": 0.25253872983481607,
        "p95": 0.32192972141772447
      },
      "191": {
        "mean": 0.2446910187004553,
        "std": 0.035739849485559194,
        "p05": 0.19036696439516182,
        "p50": 0.24319818056774123,
        "p95": 0.29620582374288185
      }
    }
  },
  "progress_fidelity_curve": {
    "shots_axis": [
      50,
      62,
      78,
      98,
      122,
      153
    ],
    "sample_reps": 30,
    "summary": {
      "50": {
        "mean": 0.4528845009098405,
        "std": 0.0705123857711623,
        "p05": 0.3360809455552179,
        "p50": 0.4689296992373115,
        "p95": 0.5555983200658392
      },
      "62": {
        "mean": 0.5416325565449335,
        "std": 0.07025734887384522,
        "p05": 0.43892716684070343,
        "p50": 0.5367340912531844,
        "p95": 0.6747167697237452
      },
      "78": {
        "mean": 0.6128604901646599,
        "std": 0.06577028613573992,
        "p05": 0.48721752310541505,
        "p50": 0.6203153157656349,
        "p95": 0.7157117475545848
      },
      "98": {
        "mean": 0.6872809537922895,
        "std": 0.05014659529292663,
        "p05": 0.6122009439794229,
        "p50": 0.6918712174376762,
        "p95": 0.7552606511659519
      },
      "122": {
        "mean": 0.7325223297769873,
        "std": 0.042865770021471246,
        "p05": 0.6482482508343955,
        "p50": 0.7385044904864402,
        "p95": 0.7841801854028221
      },
      "153": {
        "mean": 0.7838441846106742,
        "std": 0.033117717885963856,
        "p05": 0.7282832898665984,
        "p50": 0.7853976347128975,
        "p95": 0.8260597309172341
      }
    },
    "note": "PF[k] = hellinger_fidelity(dist@shots[k], dist@shots[k+1]); length N-1."
  },
  "convergence": {
    "converged": true,
    "converged_shots": 122,
    "params": {
      "N_min": 3,
      "W": 3,
      "epsilon": 0.003,
      "shots_ratio": 1.25,
      "method": "real_fidelity_slope_only"
    }
  },
  "features": {
    "depth": 364.0,
    "size": 713.0,
    "num_2q": 165.0,
    "swap": 0.0,
    "unique_2q_edges": 5.0,
    "max_2q_edge_mult": 46.0,
    "cx": 0.0,
    "ecr": 0.0,
    "cz": 165.0,
    "rz": 240.0,
    "ry": 0.0,
    "rx": 0.0,
    "sx": 302.0,
    "h": 0.0
  },
  "artifacts": {
    "dir": "shots_dataset_historic_250506/a59b0421e443ae91",
    "record_json": "shots_dataset_historic_250506/a59b0421e443ae91/record.json",
    "arrays_npz": "shots_dataset_historic_250506/a59b0421e443ae91/arrays.npz",
    "base_qasm": "shots_dataset_historic_250506/a59b0421e443ae91/base.qasm",
    "transpiled_qasm": "shots_dataset_historic_250506/a59b0421e443ae91/transpiled.qasm"
  }
}