{
  "schema_version": "v4.1",
  "created_at": "2026-04-02T17:23:38.667609+00:00",
  "record_id": "ac561da7d91a4225",
  "circuit_id": "1cef8f00b1d3e380",
  "noise_source": {
    "json_file": "ibm_pittsburgh_representative_3_2025-11-26T00_00_00_00_00.json",
    "query_datetime": "2025-11-26T00:00:00+00:00",
    "backend_name": "ibm_pittsburgh",
    "fake_backend": "fake_fez",
    "noise_summary": {
      "T1_mean": 286.3702182752811,
      "T2_mean": 343.41415954779154,
      "prob_meas0_prep1_mean": 0.010163136017628206,
      "prob_meas1_prep0_mean": 0.0031112279647435895,
      "sx_gate_error_mean": 0.006631704857789813,
      "twoq_gate_error_mean": 0.03820415699533108
    }
  },
  "transpile": {
    "optimization_level": 1,
    "seed_transpiler": 1234
  },
  "fidelity_definition": "hellinger_fidelity_(sum_sqrt(pq))^2_vs_statevector_ideal",
  "real_fidelity_curve": {
    "shots_sequence": [
      100,
      150,
      225,
      338,
      506,
      759
    ],
    "sample_reps": 30,
    "summary": {
      "100": {
        "mean": 0.9741963399476573,
        "std": 0.012668632719344512,
        "p05": 0.9514340009361923,
        "p50": 0.9772048517236589,
        "p95": 0.9871713042861459
      },
      "150": {
        "mean": 0.9795299319945301,
        "std": 0.010245847170009315,
        "p05": 0.9595118417412398,
        "p50": 0.9806443781683323,
        "p95": 0.991822173918291
      },
      "225": {
        "mean": 0.9829365678928912,
        "std": 0.00754579725657866,
        "p05": 0.9699999580506335,
        "p50": 0.983325642825074,
        "p95": 0.9935493172333983
      },
      "338": {
        "mean": 0.9866402173753808,
        "std": 0.005467551719272035,
        "p05": 0.9765408772600904,
        "p50": 0.9872915867459426,
        "p95": 0.9938260385991808
      },
      "506": {
        "mean": 0.9869553052682378,
        "std": 0.004480656394726125,
        "p05": 0.9792641978559885,
        "p50": 0.987608119103941,
        "p95": 0.9933121516576746
      },
      "759": {
        "mean": 0.9876607736221529,
        "std": 0.0035577665896634938,
        "p05": 0.9813702681748008,
        "p50": 0.9877068386313862,
        "p95": 0.9930578105417441
      }
    }
  },
  "progress_fidelity_curve": {
    "shots_axis": [
      100,
      150,
      225,
      338,
      506
    ],
    "sample_reps": 30,
    "summary": {
      "100": {
        "mean": 0.954149753926974,
        "std": 0.01915011957326427,
        "p05": 0.923849918854989,
        "p50": 0.956531711697737,
        "p95": 0.9775905641442134
      },
      "150": {
        "mean": 0.9704099008712255,
        "std": 0.015683312414936135,
        "p05": 0.9446960253033435,
        "p50": 0.9730860917757436,
        "p95": 0.9902805555675112
      },
      "225": {
        "mean": 0.9767261365619346,
        "std": 0.009301109740556616,
        "p05": 0.9658119795706778,
        "p50": 0.9764611082041892,
        "p95": 0.9906582835500826
      },
      "338": {
        "mean": 0.9823422937088558,
        "std": 0.007489043960446306,
        "p05": 0.9715330644682999,
        "p50": 0.9847065492392945,
        "p95": 0.9907980818065163
      },
      "506": {
        "mean": 0.9863738965524494,
        "std": 0.004327086760472706,
        "p05": 0.9794155555643818,
        "p50": 0.9869934211891211,
        "p95": 0.9924122482699835
      }
    },
    "note": "PF[k] = hellinger_fidelity(dist@shots[k], dist@shots[k+1]); length N-1."
  },
  "convergence": {
    "converged": true,
    "converged_shots": 338,
    "params": {
      "N_min": 4,
      "W": 3,
      "epsilon": 0.003,
      "shots_ratio": 1.5,
      "method": "real_fidelity_slope_only"
    }
  },
  "features": {
    "depth": 46.0,
    "size": 77.0,
    "num_2q": 8.0,
    "swap": 0.0,
    "unique_2q_edges": 4.0,
    "max_2q_edge_mult": 2.0,
    "cx": 0.0,
    "ecr": 0.0,
    "cz": 8.0,
    "rz": 40.0,
    "ry": 0.0,
    "rx": 0.0,
    "sx": 24.0,
    "h": 0.0
  },
  "artifacts": {
    "dir": "shots_dataset_historic2_qaoa_251126/ac561da7d91a4225",
    "record_json": "shots_dataset_historic2_qaoa_251126/ac561da7d91a4225/record.json",
    "arrays_npz": "shots_dataset_historic2_qaoa_251126/ac561da7d91a4225/arrays.npz",
    "base_qasm": "shots_dataset_historic2_qaoa_251126/ac561da7d91a4225/base.qasm",
    "transpiled_qasm": "shots_dataset_historic2_qaoa_251126/ac561da7d91a4225/transpiled.qasm"
  }
}