{
  "schema_version": "v4.1",
  "created_at": "2026-04-03T18:14:06.764002+00:00",
  "record_id": "e42ab1a93c953ad8",
  "circuit_id": "582a6de16ec7e99a",
  "noise_source": {
    "json_file": "ibm_pittsburgh_representative_5_2025-07-24T00_00_00_00_00.json",
    "query_datetime": "2025-07-24T00:00:00+00:00",
    "backend_name": "ibm_pittsburgh",
    "fake_backend": "fake_fez",
    "noise_summary": {
      "T1_mean": 295.0266644915258,
      "T2_mean": 272.2469670133587,
      "prob_meas0_prep1_mean": 0.2428886217948718,
      "prob_meas1_prep0_mean": 0.29532564603365385,
      "sx_gate_error_mean": 0.038808722855336035,
      "twoq_gate_error_mean": 0.05791100844182038
    }
  },
  "transpile": {
    "optimization_level": 1,
    "seed_transpiler": 1234
  },
  "fidelity_definition": "hellinger_fidelity_(sum_sqrt(pq))^2_vs_statevector_ideal",
  "real_fidelity_curve": {
    "shots_sequence": [
      50,
      62,
      78,
      98,
      122,
      153,
      191
    ],
    "sample_reps": 30,
    "summary": {
      "50": {
        "mean": 0.18961053059145022,
        "std": 0.046709095887954966,
        "p05": 0.14487687832323828,
        "p50": 0.18384404552104555,
        "p95": 0.2653571565465846
      },
      "62": {
        "mean": 0.20063926290132533,
        "std": 0.03310217600658304,
        "p05": 0.15402625087255326,
        "p50": 0.20045923510720537,
        "p95": 0.23982978742368513
      },
      "78": {
        "mean": 0.21283292787319558,
        "std": 0.050270484962983614,
        "p05": 0.14069820221928445,
        "p50": 0.20628852197843517,
        "p95": 0.2975838749060167
      },
      "98": {
        "mean": 0.24906166271167446,
        "std": 0.04775994094347347,
        "p05": 0.17221961823093077,
        "p50": 0.2465590129764923,
        "p95": 0.31570494422648543
      },
      "122": {
        "mean": 0.26324699366591375,
        "std": 0.03774112191189394,
        "p05": 0.2115949785617301,
        "p50": 0.25905450868778046,
        "p95": 0.3128398171363849
      },
      "153": {
        "mean": 0.26206966595855063,
        "std": 0.04033344264186496,
        "p05": 0.21203412408700217,
        "p50": 0.261410149263868,
        "p95": 0.32604787205442065
      },
      "191": {
        "mean": 0.2620120472187525,
        "std": 0.03489437981740638,
        "p05": 0.21314591037272398,
        "p50": 0.2633624725725543,
        "p95": 0.32098725820729357
      }
    }
  },
  "progress_fidelity_curve": {
    "shots_axis": [
      50,
      62,
      78,
      98,
      122,
      153
    ],
    "sample_reps": 30,
    "summary": {
      "50": {
        "mean": 0.5518134524511017,
        "std": 0.07829631826376583,
        "p05": 0.47524081423078257,
        "p50": 0.5415320225616491,
        "p95": 0.6518792387186958
      },
      "62": {
        "mean": 0.6381639187004995,
        "std": 0.059348455249564724,
        "p05": 0.5363859738625083,
        "p50": 0.6462770515446177,
        "p95": 0.7145727956116681
      },
      "78": {
        "mean": 0.677586574966348,
        "std": 0.06397113105877625,
        "p05": 0.5786737778568024,
        "p50": 0.691274682587659,
        "p95": 0.7600489084842379
      },
      "98": {
        "mean": 0.7179827011774104,
        "std": 0.04862014521895062,
        "p05": 0.6407189206260488,
        "p50": 0.7176719914925619,
        "p95": 0.7974549330903582
      },
      "122": {
        "mean": 0.7642109399735023,
        "std": 0.03990851495130791,
        "p05": 0.7114444463705037,
        "p50": 0.7671393413037115,
        "p95": 0.826285808943603
      },
      "153": {
        "mean": 0.8108742690402607,
        "std": 0.03395087368196009,
        "p05": 0.7540586327906207,
        "p50": 0.8182474114431553,
        "p95": 0.8598479826714978
      }
    },
    "note": "PF[k] = hellinger_fidelity(dist@shots[k], dist@shots[k+1]); length N-1."
  },
  "convergence": {
    "converged": true,
    "converged_shots": 122,
    "params": {
      "N_min": 3,
      "W": 3,
      "epsilon": 0.003,
      "shots_ratio": 1.25,
      "method": "real_fidelity_slope_only"
    }
  },
  "features": {
    "depth": 40.0,
    "size": 139.0,
    "num_2q": 13.0,
    "swap": 0.0,
    "unique_2q_edges": 5.0,
    "max_2q_edge_mult": 4.0,
    "cx": 0.0,
    "ecr": 0.0,
    "cz": 13.0,
    "rz": 73.0,
    "ry": 0.0,
    "rx": 0.0,
    "sx": 47.0,
    "h": 0.0
  },
  "artifacts": {
    "dir": "shots_dataset2_historic_250724/e42ab1a93c953ad8",
    "record_json": "shots_dataset2_historic_250724/e42ab1a93c953ad8/record.json",
    "arrays_npz": "shots_dataset2_historic_250724/e42ab1a93c953ad8/arrays.npz",
    "base_qasm": "shots_dataset2_historic_250724/e42ab1a93c953ad8/base.qasm",
    "transpiled_qasm": "shots_dataset2_historic_250724/e42ab1a93c953ad8/transpiled.qasm"
  }
}